scap4chan/__init__.py
scap4chan/chan.py
scap4chan-1.0.0.dist-info/METADATA
scap4chan-1.0.0.dist-info/WHEEL
scap4chan-1.0.0.dist-info/top_level.txt
scap4chan-1.0.0.dist-info/RECORD
