Metadata-Version: 2.1
Name: scap4chan
Version: 1.0.0
Author: TAWSIF AHMED
Author-email: sleeping4cat@outlook.com
Requires-Dist: BASC-py4chan
Requires-Dist: tqdm
